README.md
setup.py
grain_zip_deployer/__init__.py
grain_zip_deployer/main.py
grain_zip_deployer/settings.py
grain_zip_deployer/version.py
grain_zip_deployer.egg-info/PKG-INFO
grain_zip_deployer.egg-info/SOURCES.txt
grain_zip_deployer.egg-info/dependency_links.txt
grain_zip_deployer.egg-info/entry_points.txt
grain_zip_deployer.egg-info/requires.txt
grain_zip_deployer.egg-info/top_level.txt